podping_schemas/__init__.py
podping_schemas/org/__init__.py
podping_schemas/org/podcastindex/__init__.py
podping_schemas/org/podcastindex/podping/__init__.py
podping_schemas/org/podcastindex/podping/hivewriter/__init__.py
podping_schemas/org/podcastindex/podping/hivewriter/podping_hive_transaction.capnp
podping_schemas/org/podcastindex/podping/hivewriter/podping_hive_transaction.py
podping_schemas/org/podcastindex/podping/hivewriter/podping_hive_write.capnp
podping_schemas/org/podcastindex/podping/hivewriter/podping_hive_write.py
podping_schemas/org/podcastindex/podping/podping.capnp
podping_schemas/org/podcastindex/podping/podping.json
podping_schemas/org/podcastindex/podping/podping.py
podping_schemas/org/podcastindex/podping/podping_medium.capnp
podping_schemas/org/podcastindex/podping/podping_medium.py
podping_schemas/org/podcastindex/podping/podping_pjs.py
podping_schemas/org/podcastindex/podping/podping_reason.capnp
podping_schemas/org/podcastindex/podping/podping_reason.py
podping_schemas/org/podcastindex/podping/podping_write.capnp
podping_schemas/org/podcastindex/podping/podping_write.py
podping_schemas/org/podcastindex/podping/podping_write_error.capnp
podping_schemas/org/podcastindex/podping/podping_write_error.py
podping_schemas/rust.capnp
podping_schemas/rust.py
podping_schemas-1.0.1.dist-info/LICENSE
podping_schemas-1.0.1.dist-info/METADATA
podping_schemas-1.0.1.dist-info/WHEEL
podping_schemas-1.0.1.dist-info/RECORD
