Metadata-Version: 2.1
Name: podping-schemas
Version: 1.0.1
Summary: 
License: MIT
Author: Alecks Gates
Author-email: agates@mail.agates.io
Requires-Python: >=3.9,<3.12
Classifier: License :: OSI Approved :: MIT License
Classifier: Programming Language :: Python :: 3
Classifier: Programming Language :: Python :: 3.9
Classifier: Programming Language :: Python :: 3.10
Classifier: Programming Language :: Python :: 3.11
Requires-Dist: capnpy (>=0.10.0,<0.11.0)
Requires-Dist: python-jsonschema-objects (>=0.5.4,<0.6.0)
